minihack/__init__.py
minihack/base.py
minihack/level_generator.py
minihack/navigation.py
minihack/reward_manager.py
minihack/skills.py
minihack/version.py
minihack/wiki.py
minihack/agent/__init__.py
minihack/agent/env_names.yaml
minihack/agent/common/__init__.py
minihack/agent/common/envs/README.md
minihack/agent/common/envs/__init__.py
minihack/agent/common/envs/tasks.py
minihack/agent/common/envs/wrapper.py
minihack/agent/common/models/__init__.py
minihack/agent/common/models/dynamics.py
minihack/agent/common/models/embed.py
minihack/agent/common/models/transformer.py
minihack/agent/common/util/__init__.py
minihack/agent/common/util/id_pairs.py
minihack/agent/polybeast/__init__.py
minihack/agent/polybeast/config.yaml
minihack/agent/polybeast/evaluate.py
minihack/agent/polybeast/polybeast_env.py
minihack/agent/polybeast/polybeast_learner.py
minihack/agent/polybeast/polyhydra.py
minihack/agent/polybeast/core/file_writer.py
minihack/agent/polybeast/core/prof.py
minihack/agent/polybeast/core/vtrace.py
minihack/agent/polybeast/core/vtrace_test.py
minihack/agent/polybeast/models/__init__.py
minihack/agent/polybeast/models/base.py
minihack/agent/polybeast/models/intrinsic.py
minihack/agent/polybeast/models/losses.py
minihack/agent/rllib/__init__.py
minihack/agent/rllib/config.yaml
minihack/agent/rllib/envs.py
minihack/agent/rllib/models.py
minihack/agent/rllib/train.py
minihack/dat/chest.des
minihack/dat/closed_door.des
minihack/dat/corridor10.des
minihack/dat/corridor2.des
minihack/dat/corridor3.des
minihack/dat/corridor5.des
minihack/dat/corridor8.des
minihack/dat/exploremazeeasy.des
minihack/dat/exploremazeeasy_premapped.des
minihack/dat/exploremazehard.des
minihack/dat/exploremazehard_premapped.des
minihack/dat/hidenseek.des
minihack/dat/hidenseek_big.des
minihack/dat/hidenseek_lava.des
minihack/dat/hidenseek_mapped.des
minihack/dat/key_and_door.des
minihack/dat/key_and_door_tmp.des
minihack/dat/lava_crossing.des
minihack/dat/locked_door.des
minihack-0.1.1.dist-info/LICENSE
minihack-0.1.1.dist-info/METADATA
minihack-0.1.1.dist-info/WHEEL
minihack-0.1.1.dist-info/entry_points.txt
minihack-0.1.1.dist-info/top_level.txt
minihack-0.1.1.dist-info/RECORD
