Metadata-Version: 2.1
Name: minihack
Version: 0.1.1
Summary: MiniHack The Planet: A Sandbox for Open-Ended Reinforcement Learning Research
Home-page: https://github.com/facebookresearch/minihack
Author: The MiniHack Team
License: Apache License, Version 2.0
Platform: UNKNOWN
Classifier: License :: OSI Approved :: Apache Software License
Classifier: Development Status :: 4 - Beta
Classifier: Operating System :: POSIX :: Linux
Classifier: Operating System :: MacOS
Classifier: Programming Language :: Python :: 3
Classifier: Programming Language :: Python :: 3.7
Classifier: Programming Language :: Python :: 3.8
Classifier: Programming Language :: Python :: 3.9
Classifier: Topic :: Scientific/Engineering :: Artificial Intelligence
Classifier: Topic :: Games/Entertainment
Requires-Python: >=3.7
License-File: LICENSE
Requires-Dist: numpy (>=1.16)
Requires-Dist: gym (<0.20)
Requires-Dist: nle (>=0.7.3)
Provides-Extra: all
Requires-Dist: pre-commit (>=2.0.1) ; extra == 'all'
Requires-Dist: black (>=19.10b0) ; extra == 'all'
Requires-Dist: flake8 (>=3.7) ; extra == 'all'
Requires-Dist: flake8-bugbear (>=20.1) ; extra == 'all'
Requires-Dist: pytest (>=5.3) ; extra == 'all'
Requires-Dist: pytest-benchmark (>=3.1.0) ; extra == 'all'
Requires-Dist: sphinx (==4.0.2) ; extra == 'all'
Requires-Dist: sphinx-rtd-theme (==1.0.0) ; extra == 'all'
Requires-Dist: myst-parser (==0.15.1) ; extra == 'all'
Requires-Dist: nbsphinx (==0.8.6) ; extra == 'all'
Requires-Dist: torch (>=1.3.1) ; extra == 'all'
Requires-Dist: hydra-core (>=1.0.0) ; extra == 'all'
Requires-Dist: hydra-colorlog (>=1.0.0) ; extra == 'all'
Requires-Dist: hydra-submitit-launcher (>=1.1.1) ; extra == 'all'
Requires-Dist: wandb (>=0.10.31) ; extra == 'all'
Requires-Dist: pyyaml ; extra == 'all'
Requires-Dist: ray[rllib] (==1.3.0) ; extra == 'all'
Requires-Dist: ray[default] (==1.3.0) ; extra == 'all'
Requires-Dist: inflect ; extra == 'all'
Requires-Dist: stanza ; extra == 'all'
Provides-Extra: dev
Requires-Dist: pre-commit (>=2.0.1) ; extra == 'dev'
Requires-Dist: black (>=19.10b0) ; extra == 'dev'
Requires-Dist: flake8 (>=3.7) ; extra == 'dev'
Requires-Dist: flake8-bugbear (>=20.1) ; extra == 'dev'
Requires-Dist: pytest (>=5.3) ; extra == 'dev'
Requires-Dist: pytest-benchmark (>=3.1.0) ; extra == 'dev'
Requires-Dist: sphinx (==4.0.2) ; extra == 'dev'
Requires-Dist: sphinx-rtd-theme (==1.0.0) ; extra == 'dev'
Requires-Dist: myst-parser (==0.15.1) ; extra == 'dev'
Requires-Dist: nbsphinx (==0.8.6) ; extra == 'dev'
Provides-Extra: polybeast
Requires-Dist: torch (>=1.3.1) ; extra == 'polybeast'
Requires-Dist: hydra-core (>=1.0.0) ; extra == 'polybeast'
Requires-Dist: hydra-colorlog (>=1.0.0) ; extra == 'polybeast'
Requires-Dist: hydra-submitit-launcher (>=1.1.1) ; extra == 'polybeast'
Requires-Dist: wandb (>=0.10.31) ; extra == 'polybeast'
Requires-Dist: pyyaml ; extra == 'polybeast'
Provides-Extra: rllib
Requires-Dist: torch (>=1.3.1) ; extra == 'rllib'
Requires-Dist: ray[rllib] (==1.3.0) ; extra == 'rllib'
Requires-Dist: ray[default] (==1.3.0) ; extra == 'rllib'
Requires-Dist: hydra-core (>=1.0.0) ; extra == 'rllib'
Requires-Dist: hydra-colorlog (>=1.0.0) ; extra == 'rllib'
Requires-Dist: hydra-submitit-launcher (>=1.1.1) ; extra == 'rllib'
Requires-Dist: wandb (>=0.10.31) ; extra == 'rllib'
Provides-Extra: wiki
Requires-Dist: inflect ; extra == 'wiki'
Requires-Dist: stanza ; extra == 'wiki'
